kola/__init__.py
kola/appstack.py
kola/conf.py
kola/exceptions.py
kola/kola.py
kola/loggers.py
kola/multidict.cpython-37m-darwin.so
kola/requests.py
kola/responses.py
kola/routing.py
kola/serializers.py
kola/shortcuts.py
kola/wsgi.py
kola/plugins/__init__.py
kola/plugins/auth.py
kola/plugins/cache.py
kola/plugins/csrf.py
kola/plugins/plugin.py
kola/plugins/runtime.py
kola/plugins/sessions.py
kola_bottle-0.2.2.dist-info/LICENSE
kola_bottle-0.2.2.dist-info/METADATA
kola_bottle-0.2.2.dist-info/WHEEL
kola_bottle-0.2.2.dist-info/top_level.txt
kola_bottle-0.2.2.dist-info/RECORD
